d_fake_seeder/__init__.py
d_fake_seeder/controller.py
d_fake_seeder/dfakeseeder.desktop
d_fake_seeder/dfakeseeder.desktop.template
d_fake_seeder/dfakeseeder.py
d_fake_seeder/dfakeseeder_tray.py
d_fake_seeder/model.py
d_fake_seeder/post_install.py
d_fake_seeder/setup_helper.py
d_fake_seeder/view.py
d_fake_seeder/components/component/__init__.py
d_fake_seeder/components/component/base_component.py
d_fake_seeder/components/component/sidebar.py
d_fake_seeder/components/component/states.py
d_fake_seeder/components/component/statusbar.py
d_fake_seeder/components/component/toolbar.py
d_fake_seeder/components/component/torrents.py
d_fake_seeder/components/component/settings/__init__.py
d_fake_seeder/components/component/settings/advanced_tab.py
d_fake_seeder/components/component/settings/base_tab.py
d_fake_seeder/components/component/settings/bittorrent_tab.py
d_fake_seeder/components/component/settings/connection_tab.py
d_fake_seeder/components/component/settings/dht_tab.py
d_fake_seeder/components/component/settings/general_tab.py
d_fake_seeder/components/component/settings/multi_tracker_tab.py
d_fake_seeder/components/component/settings/peer_protocol_tab.py
d_fake_seeder/components/component/settings/protocol_extensions_tab.py
d_fake_seeder/components/component/settings/settings_dialog.py
d_fake_seeder/components/component/settings/settings_mixins.py
d_fake_seeder/components/component/settings/simulation_tab.py
d_fake_seeder/components/component/settings/speed_tab.py
d_fake_seeder/components/component/settings/webui_tab.py
d_fake_seeder/components/component/torrent_details/__init__.py
d_fake_seeder/components/component/torrent_details/base_tab.py
d_fake_seeder/components/component/torrent_details/details_tab.py
d_fake_seeder/components/component/torrent_details/files_tab.py
d_fake_seeder/components/component/torrent_details/incoming_connections_tab.py
d_fake_seeder/components/component/torrent_details/log_tab.py
d_fake_seeder-0.0.57.dist-info/licenses/LICENSE
d_fake_seeder-0.0.57.dist-info/METADATA
d_fake_seeder-0.0.57.dist-info/WHEEL
d_fake_seeder-0.0.57.dist-info/entry_points.txt
d_fake_seeder-0.0.57.dist-info/top_level.txt
d_fake_seeder-0.0.57.dist-info/RECORD
