Metadata-Version: 2.4
Name: d-fake-seeder
Version: 0.0.57
Summary: BitTorrent seeding simulator for testing and development
Home-page: https://github.com/dmzoneill/DFakeSeeder
Author: David O Neill
Author-email: dmz.oneill@gmail.com
Keywords: bittorrent torrent seeder testing development gtk4
Classifier: Development Status :: 4 - Beta
Classifier: Intended Audience :: Developers
Classifier: License :: OSI Approved :: MIT License
Classifier: Programming Language :: Python :: 3
Classifier: Programming Language :: Python :: 3.11
Classifier: Programming Language :: Python :: 3.12
Classifier: Topic :: Software Development :: Testing
Classifier: Topic :: Communications :: File Sharing
Requires-Python: >=3.11
License-File: LICENSE
Requires-Dist: requests>=2.31.0
Requires-Dist: typer>=0.12.3
Requires-Dist: urllib3>=1.26.18
Requires-Dist: PyGObject>=3.42.0
Requires-Dist: watchdog>=4.0.0
Requires-Dist: bencodepy>=0.9.5
Requires-Dist: aiohttp>=3.8.0
Requires-Dist: aiohttp-session>=2.12.0
Requires-Dist: miniupnpc>=2.2.0
Requires-Dist: pycryptodome>=3.15.0
Requires-Dist: psutil>=5.9.0
Provides-Extra: webui
Provides-Extra: upnp
Provides-Extra: encryption
Provides-Extra: all
Dynamic: author
Dynamic: author-email
Dynamic: classifier
Dynamic: description
Dynamic: description-content-type
Dynamic: home-page
Dynamic: keywords
Dynamic: license-file
Dynamic: provides-extra
Dynamic: requires-dist
Dynamic: requires-python
Dynamic: summary
